[
  {
    "id": 1764521898508,
    "description": "MEU CAVALO FICO PRESO AAAAAAAAAAAAAAAAAAAAAAAAAAAAAAAAAAAAAAAAAAAAAAA",
    "type": "arvore",
    "photoPath": "/uploads/1764521898503-694354.jpg",
    "createdAt": "2025-11-30T16:58:18.508Z",
    "location": null
  },
  {
    "id": 1764521415843,
    "description": "Eu vuei",
    "type": "outros",
    "photoPath": "/uploads/1764521415777-826680.png",
    "createdAt": "2025-11-30T16:50:15.843Z",
    "location": null
  },
  {
    "id": 1764520445621,
    "description": "QUEBRARAM UM POSTE AQUI AAAAAAAAAAAAAAAAAAAAAAAAAAAAAAAAAAAAAAAAAAAAAAAA",
    "type": "iluminacao",
    "photoPath": "/uploads/1764520445616-18062.png",
    "createdAt": "2025-11-30T16:34:05.621Z",
    "location": null
  },
  {
    "id": 1764519779862,
    "description": "UM CARA CAGOU NO MEU JARDIM",
    "type": "outros",
    "photoPath": "/uploads/1764519779845-995545.png",
    "createdAt": "2025-11-30T16:22:59.862Z",
    "location": null
  },
  {
    "id": 1764519014430,
    "description": "meu cavalo caiu de uma espcada",
    "type": "rua",
    "photoPath": "/uploads/1764519014426-205142.jpg",
    "createdAt": "2025-11-30T16:10:14.430Z",
    "location": null
  },
  {
    "id": 1764518622527,
    "description": "afafafafa",
    "type": "arvore",
    "photoPath": "/uploads/1764518622521-477064.jpg",
    "createdAt": "2025-11-30T16:03:42.527Z",
    "location": null
  }
]